mycalc/calculator.py
jaeungcalc-0.0.1.dist-info/LICENSE
jaeungcalc-0.0.1.dist-info/METADATA
jaeungcalc-0.0.1.dist-info/WHEEL
jaeungcalc-0.0.1.dist-info/top_level.txt
jaeungcalc-0.0.1.dist-info/RECORD
